[
 {
  "default_value": null,
  "doc_type": "Item",
  "docstatus": 0,
  "doctype": "Property Setter",
  "doctype_or_field": "DocType",
  "field_name": null,
  "is_system_generated": 0,
  "modified": "2025-05-17 11:52:56.867324",
  "module": null,
  "name": "Item-main-quick_entry",
  "property": "quick_entry",
  "property_type": "Check",
  "row_name": null,
  "value": "0"
 },
 {
  "default_value": null,
  "doc_type": "Item Price",
  "docstatus": 0,
  "doctype": "Property Setter",
  "doctype_or_field": "DocType",
  "field_name": null,
  "is_system_generated": 0,
  "modified": "2025-05-17 11:53:10.110427",
  "module": null,
  "name": "Item Price-main-quick_entry",
  "property": "quick_entry",
  "property_type": "Check",
  "row_name": null,
  "value": "0"
 },
 {
  "default_value": null,
  "doc_type": "Customer",
  "docstatus": 0,
  "doctype": "Property Setter",
  "doctype_or_field": "DocType",
  "field_name": null,
  "is_system_generated": 0,
  "modified": "2025-05-17 11:53:58.692927",
  "module": null,
  "name": "Customer-main-quick_entry",
  "property": "quick_entry",
  "property_type": "Check",
  "row_name": null,
  "value": "0"
 },
 {
  "default_value": null,
  "doc_type": "Supplier",
  "docstatus": 0,
  "doctype": "Property Setter",
  "doctype_or_field": "DocType",
  "field_name": null,
  "is_system_generated": 0,
  "modified": "2025-05-17 11:54:12.346843",
  "module": null,
  "name": "Supplier-main-quick_entry",
  "property": "quick_entry",
  "property_type": "Check",
  "row_name": null,
  "value": "0"
 },
 {
  "default_value": null,
  "doc_type": "Sales Invoice Item",
  "docstatus": 0,
  "doctype": "Property Setter",
  "doctype_or_field": "DocType",
  "field_name": null,
  "is_system_generated": 0,
  "modified": "2025-05-17 12:06:54.562566",
  "module": null,
  "name": "Sales Invoice Item-main-field_order",
  "property": "field_order",
  "property_type": "Data",
  "row_name": null,
  "value": "[\"barcode\", \"has_item_scanned\", \"adist_item_group\", \"adist_item\", \"item_code\", \"col_break1\", \"item_name\", \"customer_item_code\", \"description_section\", \"description\", \"item_group\", \"brand\", \"image_section\", \"image\", \"image_view\", \"quantity_and_rate\", \"qty\", \"stock_uom\", \"col_break2\", \"uom\", \"conversion_factor\", \"stock_qty\", \"section_break_17\", \"price_list_rate\", \"base_price_list_rate\", \"discount_and_margin\", \"margin_type\", \"margin_rate_or_amount\", \"rate_with_margin\", \"column_break_19\", \"discount_percentage\", \"discount_amount\", \"discount_total\", \"base_rate_with_margin\", \"section_break1\", \"rate\", \"amount\", \"total_value\", \"item_tax_template\", \"col_break3\", \"base_rate\", \"base_amount\", \"pricing_rules\", \"stock_uom_rate\", \"is_free_item\", \"grant_commission\", \"section_break_21\", \"net_rate\", \"net_amount\", \"column_break_24\", \"base_net_rate\", \"base_net_amount\", \"drop_ship\", \"delivered_by_supplier\", \"accounting\", \"income_account\", \"is_fixed_asset\", \"asset\", \"finance_book\", \"col_break4\", \"expense_account\", \"discount_account\", \"deferred_revenue\", \"deferred_revenue_account\", \"service_stop_date\", \"enable_deferred_revenue\", \"column_break_50\", \"service_start_date\", \"service_end_date\", \"section_break_18\", \"weight_per_unit\", \"total_weight\", \"column_break_21\", \"weight_uom\", \"warehouse_and_reference\", \"warehouse\", \"target_warehouse\", \"quality_inspection\", \"batch_no\", \"incoming_rate\", \"col_break5\", \"allow_zero_valuation_rate\", \"serial_no\", \"item_tax_rate\", \"actual_batch_qty\", \"actual_qty\", \"edit_references\", \"sales_order\", \"so_detail\", \"sales_invoice_item\", \"column_break_74\", \"delivery_note\", \"dn_detail\", \"delivered_qty\", \"internal_transfer_section\", \"purchase_order\", \"column_break_92\", \"purchase_order_item\", \"accounting_dimensions_section\", \"cost_center\", \"dimension_col_break\", \"project\", \"section_break_54\", \"page_break\"]"
 },
 {
  "default_value": null,
  "doc_type": "Sales Invoice Item",
  "docstatus": 0,
  "doctype": "Property Setter",
  "doctype_or_field": "DocField",
  "field_name": "item_code",
  "is_system_generated": 0,
  "modified": "2025-05-17 12:10:59.649894",
  "module": null,
  "name": "Sales Invoice Item-item_code-fetch_from",
  "property": "fetch_from",
  "property_type": "Small Text",
  "row_name": null,
  "value": "adist_item.item_code"
 },
 {
  "default_value": null,
  "doc_type": "Stock Entry",
  "docstatus": 0,
  "doctype": "Property Setter",
  "doctype_or_field": "DocField",
  "field_name": "section_break_jwgn",
  "is_system_generated": 0,
  "modified": "2025-05-28 11:35:52.451550",
  "module": null,
  "name": "Stock Entry-section_break_jwgn-collapsible",
  "property": "collapsible",
  "property_type": "Check",
  "row_name": null,
  "value": "0"
 },
 {
  "default_value": null,
  "doc_type": "Customer",
  "docstatus": 0,
  "doctype": "Property Setter",
  "doctype_or_field": "DocType",
  "field_name": null,
  "is_system_generated": 0,
  "modified": "2023-11-11 16:29:55.107302",
  "module": null,
  "name": "Customer-main-field_order",
  "property": "field_order",
  "property_type": "Data",
  "row_name": null,
  "value": "[\"basic_info\", \"naming_series\", \"salutation\", \"customer_name\", \"customer_type\", \"customer_group\", \"excel_actual_cust_code\", \"excel_customer_bin_id\", \"excel_customer_trade_license\", \"excel_customer_nid\", \"excel_security_cheque_amount\", \"column_break0\", \"territory\", \"gender\", \"lead_name\", \"excel_customer_tin_id\", \"excel_customer_owner_name\", \"excel_customer_owner_fathers_name\", \"excel_customer_owners_permanent_address\", \"opportunity_name\", \"account_manager\", \"image\", \"defaults_tab\", \"default_price_list\", \"default_bank_account\", \"column_break_14\", \"default_currency\", \"internal_customer_section\", \"is_internal_customer\", \"represents_company\", \"column_break_70\", \"companies\", \"more_info\", \"market_segment\", \"industry\", \"customer_pos_id\", \"website\", \"language\", \"column_break_45\", \"customer_details\", \"dashboard_tab\", \"contact_and_address_tab\", \"address_contacts\", \"address_html\", \"column_break1\", \"contact_html\", \"primary_address_and_contact_detail\", \"customer_primary_contact\", \"mobile_no\", \"email_id\", \"column_break_26\", \"customer_primary_address\", \"primary_address\", \"tax_tab\", \"taxation_section\", \"tax_id\", \"column_break_21\", \"tax_category\", \"tax_withholding_category\", \"accounting_tab\", \"credit_limit_section\", \"payment_terms\", \"excel_fixed_credit_limit\", \"excel_unpaid_vs_fcl\", \"excel_allow_unfreeze\", \"credit_limits\", \"default_receivable_accounts\", \"accounts\", \"loyalty_points_tab\", \"loyalty_program\", \"column_break_54\", \"loyalty_program_tier\", \"sales_team_tab\", \"excel_sales_person_email\", \"excel_sales_person\", \"sales_team\", \"sales_team_section\", \"default_sales_partner\", \"column_break_66\", \"default_commission_rate\", \"settings_tab\", \"so_required\", \"dn_required\", \"column_break_53\", \"is_frozen\", \"disabled\"]"
 }
]